Workbook

Sheet Legenda
A1: Planilha de testes: Verzel Store (VZS-142, v2.3.0)
A3: Aba | B3: Para que serve
A4: Calculadora | B4: Digite quantidades e escolha o cupom. A planilha calcula o valor ESPERADO (subtotal, desconto, frete, faltante, total). Calcule antes de olhar a loja.
A5: Casos Manuais | B5: Roteiro dos testes de UI. Preencha as colunas amarelas: Resultado obtido, Status, Bug, Evidência, Data.
A6: Casos API | B6: Roteiro dos testes de API (Postman/curl). Mesmas colunas amarelas.
A7: Bugs | B7: Registro dos bugs encontrados. A linha BUG-EXEMPLO mostra o formato (apague ou substitua).
A8: Ambiguidades | B8: Pontos em que a documentação não define o comportamento. Escreva a interpretação adotada.
A9: Resumo | B9: Contagens automáticas por status e por grupo. Não precisa editar.
A10: Produtos e Cupons | B10: Dados fixos da documentação (usados pela Calculadora).
A12: Convenções
A13: Células amarelas | B13: Você preenche.
A14: Texto azul | B14: Valor de entrada (editável).
A15: Status | B15: Escolha na lista: Passou, Falhou, Bloqueado, Dúvida, Não executado.
A16: Esperado | B16: Valores calculados a partir das regras da documentação (CA01 a CA11). Se a loja divergir, é candidato a bug.
A17: Fora do escopo | B17: Carga, estresse, segurança, login, pagamento online, consulta de pedidos. O que está em &apos;Sobre este ambiente&apos; não é bug.

Sheet Calculadora
A1: Calculadora de valores esperados
A2: Preencha as células amarelas. Fórmula: total = subtotal − desconto + frete. Valores arredondados a 2 casas (CA11).
A4: Id | B4: Produto | C4: Preço unit. | D4: Quantidade | E4: Total do item | F4: Qtd válida? (≤5)
A5: =&apos;Produtos e Cupons&apos;!A2 | B5: =&apos;Produtos e Cupons&apos;!B2 | C5: =&apos;Produtos e Cupons&apos;!C2 | D5: 0 | E5: =ROUND(C5*D5,2) | F5: =IF(D5>&apos;Produtos e Cupons&apos;!$C$15,"EXCEDE (422)","ok")
A6: =&apos;Produtos e Cupons&apos;!A3 | B6: =&apos;Produtos e Cupons&apos;!B3 | C6: =&apos;Produtos e Cupons&apos;!C3 | D6: 0 | E6: =ROUND(C6*D6,2) | F6: =IF(D6>&apos;Produtos e Cupons&apos;!$C$15,"EXCEDE (422)","ok")
A7: =&apos;Produtos e Cupons&apos;!A4 | B7: =&apos;Produtos e Cupons&apos;!B4 | C7: =&apos;Produtos e Cupons&apos;!C4 | D7: 0 | E7: =ROUND(C7*D7,2) | F7: =IF(D7>&apos;Produtos e Cupons&apos;!$C$15,"EXCEDE (422)","ok")
A8: =&apos;Produtos e Cupons&apos;!A5 | B8: =&apos;Produtos e Cupons&apos;!B5 | C8: =&apos;Produtos e Cupons&apos;!C5 | D8: 0 | E8: =ROUND(C8*D8,2) | F8: =IF(D8>&apos;Produtos e Cupons&apos;!$C$15,"EXCEDE (422)","ok")
A9: =&apos;Produtos e Cupons&apos;!A6 | B9: =&apos;Produtos e Cupons&apos;!B6 | C9: =&apos;Produtos e Cupons&apos;!C6 | D9: 0 | E9: =ROUND(C9*D9,2) | F9: =IF(D9>&apos;Produtos e Cupons&apos;!$C$15,"EXCEDE (422)","ok")
A10: =&apos;Produtos e Cupons&apos;!A7 | B10: =&apos;Produtos e Cupons&apos;!B7 | C10: =&apos;Produtos e Cupons&apos;!C7 | D10: 0 | E10: =ROUND(C10*D10,2) | F10: =IF(D10>&apos;Produtos e Cupons&apos;!$C$15,"EXCEDE (422)","ok")
A11: =&apos;Produtos e Cupons&apos;!A8 | B11: =&apos;Produtos e Cupons&apos;!B8 | C11: =&apos;Produtos e Cupons&apos;!C8 | D11: 0 | E11: =ROUND(C11*D11,2) | F11: =IF(D11>&apos;Produtos e Cupons&apos;!$C$15,"EXCEDE (422)","ok")
A12: =&apos;Produtos e Cupons&apos;!A9 | B12: =&apos;Produtos e Cupons&apos;!B9 | C12: =&apos;Produtos e Cupons&apos;!C9 | D12: 0 | E12: =ROUND(C12*D12,2) | F12: =IF(D12>&apos;Produtos e Cupons&apos;!$C$15,"EXCEDE (422)","ok")
A14: Cupom | B14: (sem cupom)
A16: Percentual do cupom válido | B16: =IF(B14="BEMVINDO10",&apos;Produtos e Cupons&apos;!F2,0)
A17: Situação do cupom | B17: =IF(B14="BEMVINDO10","Aplicado",IF(B14="VERAO2026","Cupom expirado.",IF(B14="NAOEXISTE","Cupom inválido.","Sem cupom")))
A18: Subtotal | B18: =ROUND(SUM(E5:E12),2)
A19: Desconto (sobre subtotal, CA01/CA09) | B19: =ROUND(B18*B16,2)
A20: Frete (CA06/CA07/CA08) | B20: =IF(B18=0,0,IF(B18>=&apos;Produtos e Cupons&apos;!C13,0,&apos;Produtos e Cupons&apos;!C14))
A21: Faltante p/ frete grátis | B21: =IF(B18=0,0,ROUND(MAX(0,&apos;Produtos e Cupons&apos;!C13-B18),2))
A22: TOTAL esperado | B22: =ROUND(B18-B19+B20,2)
A24: Observações: subtotal vazio (carrinho vazio) assume frete R$ 0,00 e faltante R$ 0,00 só para evitar confusão; o comportamento real do carrinho vazio deve ser anotado como dúvida.
A25: Premissa: arredondamento comercial (ROUND do Excel). Ver aba Ambiguidades.

Sheet Produtos e Cupons
A1: Id | B1: Produto | C1: Preço (R$) | E1: Cupom | F1: Desconto | G1: Situação
A2: P001 | B2: Camiseta Essencial | C2: 59.9 | E2: BEMVINDO10 | F2: 0.1 | G2: Válido
A3: P002 | B3: Calça Jeans Slim | C3: 139.9 | E3: VERAO2026 | F3: 0.15 | G3: Expirado em 31/03/2026
A4: P003 | B4: Tênis Casual Urbano | C4: 189.9 | E4: (sem cupom) | F4: 0 | G4: -
A5: P004 | B5: Boné Aba Curva | C5: 49.9 | E5: NAOEXISTE | F5: 0 | G5: Inexistente
A6: P005 | B6: Mochila Urbana 20L | C6: 100
A7: P006 | B7: Kit 3 Pares de Meias | C7: 29.9
A8: P007 | B8: Jaqueta Corta-Vento | C8: 229.9
A9: P008 | B9: Garrafa Térmica 750ml | C9: 50
A12: Regras fixas
A13: Frete grátis a partir de (R$) | C13: 200
A14: Frete fixo (R$) | C14: 19.9
A15: Máximo por produto | C15: 5
A17: Fonte: documentação do card VZS-142 (valores informados pelo enunciado).

Sheet Casos Manuais
A1: ID | B1: Grupo | C1: CA | D1: Cenário | E1: Pré-condição | F1: Passos | G1: Resultado esperado | H1: Resultado obtido | I1: Status | J1: Bug | K1: Evidência (arquivo) | L1: Data
A2: CT-A1 | B2: A. Cupom | C2: CA01 | D2: Aplicar BEMVINDO10 | E2: Carrinho vazio | F2: 1. Adicionar 1× Mochila Urbana 20L&#10;2. Abrir carrinho&#10;3. Digitar BEMVINDO10 e aplicar | G2: Subtotal 100,00 | Desconto 10,00 | Frete 19,90 | Faltante 100,00 | Total 109,90 | I2: Não executado
A3: CT-A2a | B3: A. Cupom | C3: CA02 | D3: Cupom em minúsculas | E3: 1× Mochila no carrinho | F3: Aplicar &apos;bemvindo10&apos; | G3: Desconto 10,00 | Total 109,90 | H3: passou | I3: aceita
A4: CT-A2b | B4: A. Cupom | C4: CA02 | D4: Cupom com caixa mista | E4: 1× Mochila no carrinho | F4: Aplicar &apos;BemVindo10&apos; | G4: Desconto 10,00 | Total 109,90 | H4: passou | I4: aceita
A5: CT-A2c | B5: A. Cupom | C5: CA02 | D5: Espaços no início | E5: 1× Mochila no carrinho | F5: Aplicar &apos; BEMVINDO10&apos; | G5: Desconto 10,00 | Total 109,90 | H5: passou | I5: aceita
A6: CT-A2d | B6: A. Cupom | C6: CA02 | D6: Espaços no fim | E6: 1× Mochila no carrinho | F6: Aplicar &apos;BEMVINDO10 &apos; | G6: Desconto 10,00 | Total 109,90 | H6: passou | I6: aceita
A7: CT-A2e | B7: A. Cupom | C7: CA02 | D7: Espaço no meio (ambiguidade) | E7: 1× Mochila no carrinho | F7: Aplicar &apos;BEM VINDO10&apos; | G7: Não definido na doc. Registrar o que ocorre e a interpretação (provável: cupom inválido). | H7: rejeitado | I7: falhou
A8: CT-A3 | B8: A. Cupom | C8: CA03 | D8: Cupom inexistente | E8: 1× Mochila no carrinho | F8: Aplicar &apos;NAOEXISTE&apos; | G8: Mensagem exata &apos;Cupom inválido.&apos; | Desconto 0 | Total 119,90 | H8: rejeitado | I8: falhou
A9: CT-A4 | B9: A. Cupom | C9: CA04 | D9: Cupom expirado | E9: 1× Mochila no carrinho | F9: Aplicar &apos;VERAO2026&apos; | G9: Mensagem exata &apos;Cupom expirado.&apos; | Desconto 0 | Total 119,90 | H9: rejeitado | I9: falhou
A10: CT-A5 | B10: A. Cupom | C10: CA05 | D10: Apenas um cupom por vez | E10: BEMVINDO10 já aplicado | F10: 1. Tentar aplicar outro cupom sem remover&#10;2. Remover o cupom&#10;3. Aplicar VERAO2026 | G10: Passo 1: UI impede ou exige remover. Passo 3: desconto do BEMVINDO10 desaparece e aparece &apos;Cupom expirado.&apos; | I10: Não executado
A11: CT-A6 | B11: A. Cupom | C11: CA01 | D11: Cupom recalcula ao mudar quantidade | E11: BEMVINDO10 aplicado com 1× Mochila | F11: Mudar a quantidade da Mochila para 2 | G11: Subtotal 200,00 | Desconto 20,00 | Frete 0,00 | Total 180,00 | I11: Não executado
A12: CT-A7 | B12: A. Cupom | C12: CA03 | D12: Cupom vazio | E12: 1× Mochila no carrinho | F12: Clicar em aplicar sem digitar | G12: Nada é aplicado; mensagem clara (anotar). Não deve quebrar a tela. | I12: Não executado
A13: CT-A8 | B13: A. Cupom | C13: CA01 | D13: Aplicar cupom antes de adicionar produto | E13: Carrinho vazio | F13: Aplicar BEMVINDO10, depois adicionar 1× Mochila | G13: Anotar. Se o cupom fica aplicado: desconto 10,00 | Total 109,90. | I13: Não executado
A14: CT-A9 | B14: A. Cupom | C14: CA01 | D14: Esvaziar carrinho com cupom aplicado | E14: BEMVINDO10 aplicado | F14: Remover todos os itens | G14: Sem valores negativos; sem desconto fantasma (anotar). | I14: Não executado
A15: CT-B1a | B15: B. Frete | C15: CA06 | D15: Limite exato R$ 200,00 (Mochila) | E15: Carrinho vazio | F15: Adicionar 2× Mochila | G15: Subtotal 200,00 | Frete 0,00 | Faltante 0,00 | Total 200,00 | H15: Subtotal R$ 200,00 correto. Frete R$ 19,90 (esperado R$ 0,00). | I15: Falhou | J15: BUG-001 | K15: evidencias/ui/CT-B1a-falhou.png | L15: 46244
A16: CT-B1b | B16: B. Frete | C16: CA06 | D16: Limite exato R$ 200,00 (Garrafa) | E16: Carrinho vazio | F16: Adicionar 4× Garrafa Térmica 750ml | G16: Subtotal 200,00 | Frete 0,00 | Total 200,00 | H16: Subtotal R$ 200,00 correto. Frete R$ 19,90 (esperado R$ 0,00). | I16: Falhou | J16: BUG-001 | K16: evidencias/ui/CT-B1b-falhou.png | L16: 46244
A17: CT-B2 | B17: B. Frete | C17: CA07 | D17: Um passo abaixo do limite | E17: Carrinho vazio | F17: Adicionar 1× Camiseta + 1× Calça Jeans | G17: Subtotal 199,80 | Frete 19,90 | Faltante 0,20 | Total 219,70 | I17: Não executado
A18: CT-B3 | B18: B. Frete | C18: CA07 | D18: Frete fixo e aviso de faltante | E18: Carrinho vazio | F18: Adicionar 1× Mochila | G18: Frete 19,90 | Aviso: faltam R$ 100,00 | Total 119,90 | I18: Não executado
A19: CT-B4 | B19: B. Frete | C19: CA08 | D19: Frete usa subtotal ANTES do cupom | E19: Carrinho vazio | F19: Adicionar 2× Mochila e aplicar BEMVINDO10 | G19: Desconto 20,00 | Frete 0,00 | Total 180,00 (se o frete virar 19,90, viola CA08) | H19: Subtotal R$ 200,00 e desconto R$ 20,00 corretos. Frete R$ 19,90 (esperado R$ 0,00). | I19: Falhou | J19: BUG-001 | K19: evidencias/ui/CT-B4-falhou.png | L19: 46244
A20: CT-B5 | B20: B. Frete | C20: CA09 | D20: Desconto não incide sobre o frete | E20: Carrinho vazio | F20: Adicionar Camiseta + Calça e aplicar BEMVINDO10 | G20: Subtotal 199,80 | Desconto 19,98 | Frete 19,90 (inteiro) | Total 199,72 | I20: Não executado
A21: CT-B6 | B21: B. Frete | C21: CA06 | D21: Frete grátis bem acima do limite | E21: Carrinho vazio | F21: Adicionar 1× Jaqueta Corta-Vento | G21: Subtotal 229,90 | Frete 0,00 | Faltante 0,00 (mensagem oculta ou R$ 0,00) | Total 229,90 | I21: Não executado
A22: CT-B7 | B22: B. Frete | C22: CA06 | D22: Cruzar o limite subindo e descendo | E22: Carrinho vazio | F22: 1. 2× Mochila (200,00)&#10;2. Reduzir para 1× (100,00)&#10;3. Subir de novo para 2× | G22: Frete 0,00 → 19,90 → 0,00 e faltante atualiza a cada passo | I22: Não executado
A23: CT-B8 | B23: B. Frete | C23: CA06 | D23: Cupom + subtotal logo abaixo do limite | E23: Carrinho vazio | F23: Camiseta + Calça + BEMVINDO10 | G23: Frete 19,90 (subtotal 199,80 < 200,00) | Total 199,72 | I23: Não executado
A24: CT-C1 | B24: C. Quantidade | C24: CA10 | D24: Exatamente 5 unidades | E24: Carrinho vazio | F24: Adicionar 5× Garrafa Térmica | G24: Aceita | Subtotal 250,00 | Frete 0,00 | Total 250,00 | I24: Não executado
A25: CT-C2a | B25: C. Quantidade | C25: CA10 | D25: 6 unidades pelo botão + | E25: 5× Garrafa no carrinho | F25: Clicar em + de novo | G25: Bloqueia ou avisa; quantidade permanece 5 | I25: Não executado
A26: CT-C2b | B26: C. Quantidade | C26: CA10 | D26: 6 unidades digitando no campo | E26: Carrinho com Garrafa | F26: Digitar 6 no campo de quantidade | G26: Bloqueia, ajusta para 5 ou mostra erro; nunca aceita 6 em silêncio | I26: Não executado
A27: CT-C2c | B27: C. Quantidade | C27: CA10 | D27: 6 unidades via &apos;Adicionar&apos; repetido | E27: Carrinho vazio | F27: Clicar 6× em Adicionar na lista de produtos | G27: Soma não passa de 5 (ambiguidade: registrar o comportamento) | I27: Não executado
A28: CT-C2d | B28: C. Quantidade | C28: CA10 | D28: Limite aplicado em cada produto separadamente | E28: Carrinho vazio | F28: 5× Garrafa + 5× Boné | G28: Aceita (limite é por produto) | Subtotal 499,50 | I28: Não executado
A29: CT-C3 | B29: C. Quantidade | C29: CA10 | D29: Valores inválidos no campo | E29: 1× Garrafa no carrinho | F29: Digitar: 0, -1, 1,5, abc, 99, vazio | G29: Nenhum valor inválido é aceito em silêncio; anotar o resultado de cada um | I29: Não executado
A30: CT-C4 | B30: C. Quantidade | C30: — | D30: Reduzir abaixo de 1 | E30: 1× produto no carrinho | F30: Clicar em − com quantidade 1 | G30: Remove o item ou bloqueia (anotar); sem quantidade 0 ou negativa | I30: Não executado
A31: CT-D1 | B31: D. Arredondamento | C31: CA11 | D31: 3× Camiseta com cupom | E31: Carrinho vazio | F31: Adicionar 3× Camiseta e aplicar BEMVINDO10 | G31: Subtotal 179,70 | Desconto 17,97 | Frete 19,90 | Faltante 20,30 | Total 181,63 | I31: Não executado
... A53: CT-F6 | B53: F. Exploratório | C53: — | D53: Carrinho vazio | E53: Carrinho vazio | F53: Abrir o carrinho e tentar finalizar | G53: Mensagem amigável; não permite confirmar pedido vazio | I53: Não executado

Sheet Casos API
A1: ID | B1: Endpoint | C1: Cenário | D1: Requisição (resumo) | E1: Status HTTP esperado | F1: Código/Resultado esperado | G1: Resultado obtido | H1: Status | I1: Bug | J1: Evidência | K1: Data
A2: API-01 | B2: GET /api/produtos | C2: Listar produtos | D2: GET | E2: 200 | F2: 8 produtos com id, nome, descricao, categoria, preco; preços conforme tabela | H2: Não executado
A3: API-02 | B3: GET /api/produtos/{id} | C3: Id existente | D3: GET /api/produtos/P001 | E3: 200 | F3: Produto P001, Camiseta Essencial, preco 59.9 | H3: Não executado
A4: API-03 | B4: GET /api/produtos/{id} | C4: Id inexistente | D4: GET /api/produtos/P999 | E4: 404 | F4: erro.codigo = PRODUTO_NAO_ENCONTRADO | H4: Não executado
A5: API-04 | B5: /api/produtos | C5: Método não permitido | D5: POST /api/produtos | E5: 405 | F5: METODO_NAO_PERMITIDO | H5: Não executado
A6: API-05 | B6: /api/xyz | C6: Rota inexistente | D6: GET /api/xyz | E6: 404 | F6: ROTA_NAO_ENCONTRADA | H6: Não executado
A7: API-06 | B7: POST /api/carrinho/calcular | C7: Sem cupom, abaixo de 200 | D7: itens: P005×1 | E7: 200 | F7: subtotal 100 | desconto 0 | frete 19.9 | freteGratis false | faltante 100 | total 119.9 | H7: Não executado
A8: API-07 | B8: POST /api/carrinho/calcular | C8: Cupom válido | D8: itens: P005×1, cupom BEMVINDO10 | E8: 200 | F8: desconto 10 | frete 19.9 | total 109.9 | cupom.aplicado true | H8: Não executado
A9: API-08 | B9: POST /api/carrinho/calcular | C9: Limite 200,00 exato | D9: itens: P005×2 | E9: 200 | F9: frete 0 | freteGratis true | faltante 0 | total 200 | H9: Não executado
A10: API-09 | B10: POST /api/carrinho/calcular | C10: Frete grátis usa subtotal antes do cupom | D10: itens: P005×2, cupom BEMVINDO10 | E10: 200 | F10: subtotal 200 | desconto 20 | frete 0 | total 180 | H10: Não executado
A11: API-10 | B11: POST /api/carrinho/calcular | C11: Desconto não incide no frete | D11: itens: P001×1 + P002×1, cupom BEMVINDO10 | E11: 200 | F11: subtotal 199.8 | desconto 19.98 | frete 19.9 | faltante 0.2 | total 199.72 | H11: Não executado
A12: API-11 | B12: POST /api/carrinho/calcular | C12: Exemplo da documentação | D12: itens: P002×1 + P004×2, cupom BEMVINDO10 | E12: 200 | F12: subtotal 239.7 | desconto 23.97 | frete 0 | total 215.73 | H12: Não executado
A13: API-12 | B13: POST /api/carrinho/calcular | C13: Arredondamento (float) | D13: itens: P001×3, cupom BEMVINDO10 | E13: 200 | F13: subtotal 179.7 | desconto 17.97 | total 181.63 (nenhum valor com 15+ casas, ex.: 179.70000000000002) | H13: Não executado
... A18: API-17 | B18: POST /api/carrinho/calcular | C18: Cupom null / vazio / só espaços | D18: cupom null, "", " " | E18: 200 | F18: Anotar (ambiguidade). Provável: tratado como sem cupom. | H18: Não executado
A19: API-18 | B19: POST /api/carrinho/calcular | C19: Cupom em tipo errado | D19: cupom 123 e cupom {} | E19: a anotar | F19: Anotar comportamento (ambiguidade); não deve ser erro 500 | H19: Não executado
A20: API-19 | B20: POST /api/carrinho/calcular | C20: Corpo não-JSON | D20: body: {abc | E20: 400 | F20: JSON_INVALIDO | H20: Não executado
A21: API-20 | B21: POST /api/carrinho/calcular | C21: itens ausente | D21: {} | E21: 422 | F21: ITENS_OBRIGATORIOS | H21: Não executado
A22: API-21 | B22: POST /api/carrinho/calcular | C22: itens vazio | D22: itens: [] | E22: 422 | F22: ITENS_OBRIGATORIOS | H22: Não executado
A23: API-22 | B23: POST /api/carrinho/calcular | C23: item não é objeto | D23: itens: ["P001"] | E23: 422 | F23: ITEM_INVALIDO | H23: Não executado
A24: API-23 | B24: POST /api/carrinho/calcular | C24: item sem produtoId | D24: itens: [{"quantidade":1}] | E24: 422 | F24: ITEM_INVALIDO | H24: Não executado
A25: API-24 | B25: POST /api/carrinho/calcular | C25: produto inexistente | D25: itens: P999×1 | E25: 422 | F25: PRODUTO_NAO_ENCONTRADO | H25: Não executado
A26: API-25 | B26: POST /api/carrinho/calcular | C26: produto duplicado | D26: itens: P001×1 e P001×2 | E26: 422 | F26: ITEM_DUPLICADO | H26: Não executado
A27: API-26 | B27: POST /api/carrinho/calcular | C27: quantidade 0 | D27: P001×0 | E27: 422 | F27: QUANTIDADE_INVALIDA | H27: Não executado
A28: API-27 | B28: POST /api/carrinho/calcular | C28: quantidade negativa | D28: P001×-1 | E28: 422 | F28: QUANTIDADE_INVALIDA | H28: Não executado
A29: API-28 | B29: POST /api/carrinho/calcular | C29: quantidade decimal | D29: P001×1.5 | E29: 422 | F29: QUANTIDADE_INVALIDA | H29: Não executado
A30: API-29 | B30: POST /api/carrinho/calcular | C30: quantidade como string | D30: P001×"2" | E30: 422 | F30: QUANTIDADE_INVALIDA | H30: Não executado
A31: API-30 | B31: POST /api/carrinho/calcular | C31: quantidade null | D31: P001×null | E31: 422 | F31: QUANTIDADE_INVALIDA | H31: Não executado
... A47: API-46 | B47: POST /api/pedidos | C47: Erros combinados | D47: cliente inválido + quantidade 6 | E47: 422 | F47: Anotar qual erro vem primeiro (ambiguidade: ordem de validação) | H47: Não executado
A48: API-47 | B48: Todas | C48: Formato do erro | D48: Qualquer resposta de erro | E48: — | F48: JSON {erro:{codigo,mensagem,campo}} e Content-Type application/json | H48: Não executado
A49: API-48 | B49: Todas | C49: Valores com no máximo 2 casas decimais | D49: Todas as respostas 200/201 | E49: — | F49: Nenhum número com ruído de ponto flutuante | H49: Não executado
A50: API-49 | B50: POST /api/carrinho/calcular | C50: Paridade UI × API | D50: Carrinho na tela vs. resposta no Network | E50: 200 | F50: Mesmos valores | H50: Não executado
A52: Corpo base dos pedidos: {"cliente":{"nome":"Maria Silva","email":"maria@exemplo.com","cep":"01310-100"},"itens":[...],"cupom":"..."}. Base URL: https://verzel-store.qa-test-verzel-store.workers.dev

Sheet Bugs
A1: ID | B1: Título | C1: Severidade | D1: Prioridade | E1: CA violado | F1: Camada (UI/API) | G1: Pré-condição | H1: Passos para reproduzir | I1: Resultado esperado | J1: Resultado obtido | K1: Evidência | L1: Caso relacionado | M1: Reprodutível? | N1: Status do bug
A2: BUG-EXEMPLO | B2: (EXEMPLO de formato, apague) Frete cobrado com subtotal exatamente R$ 200,00 | C2: Alta | D2: Alta | E2: CA06 | F2: UI e API | G2: Carrinho vazio | H2: 1. Adicionar 2× Mochila Urbana 20L&#10;2. Abrir o carrinho | I2: Frete R$ 0,00 e total R$ 200,00 | J2: Frete R$ 19,90 e total R$ 219,90 | K2: evidencias/BUG-001.png | L2: CT-B1a | M2: 3/3 | N2: Aberto
A3: BUG-001 | B3: Frete é cobrado (R$ 19,90) quando o subtotal é exatamente R$ 200,00 | C3: Alta | D3: Alta | E3: CA06 | F3: UI (confirmar a API, veja a seção 4) | G3: Carrinho vazio, sem cupom aplicado | H3: 1. Abrir a loja. 2. Adicionar 2 unidades de "Mochila Urbana 20L" (R$ 100,00 cada). 3. Abrir o carrinho. 4. Ver o "Resumo do pedido". | I3: Subtotal R$ 200,00, Frete R$ 0,00 (grátis). O CA06 diz "a partir de R$ 200,00, inclusive". | J3: Subtotal R$ 200,00, mas Frete R$ 19,90. Também acontece com 4× Garrafa Térmica 750ml e com 2× Mochila + BEMVINDO10. | K3: evidencias/ui/BUG-001.png | L3: CT-B1a, CT-B1b, CT-B4 | M3: Sim: 3 de 3 cenários (confirme na mão e anote "3/3") | N3: Aberto
A4: BUG-002 | B4: API aceita quantidade acima de 5 por produto em /api/carrinho/calcular e /api/pedidos | C4: Alta | D4: Alta | E4: CA10 | F4: API | G4: Nenhuma | H4: 1. Enviar POST /api/carrinho/calcular com itens P008, quantidade 6. 2. Repetir com quantidade 100. 3. Enviar POST /api/pedidos com cliente válido e itens P008, quantidade 6. | I4: Status 422 com erro.codigo = QUANTIDADE_MAXIMA_EXCEDIDA nos três casos. O CA10 diz que a regra vale para a interface e para a API. | J4: calcular: status 200, com subtotal R$ 300,00 (quantidade 6) e R$ 5.000,00 (quantidade 100). pedidos: status 201, pedido confirmado (VZ-483484) com quantidade 6 e total R$ 300,00. A interface bloqueia em 5 (botão desabilitado e aviso "Limite de 5 unidades atingido."), então o limite só existe na tela. | K4: evidencias/api/BUG-002-calcular.png e evidencias/api/BUG-002-pedidos.png | L4: API-32, API-44 | M4: Sim (3 de 3) | N4: Aberto
A5: BUG-003 | B5: Item sem produtoId retorna PRODUTO_NAO_ENCONTRADO em vez de ITEM_INVALIDO | C5: Baixa | D5: Baixa | E5: Tabela de códigos de erro da API (ITEM_INVALIDO) | F5: API | G5: Nenhuma | H5: 1. Enviar POST /api/carrinho/calcular com itens [{"quantidade":1}] (sem produtoId). | I5: Status 422 com código ITEM_INVALIDO. A documentação diz: "Um item não é um objeto com produtoId e quantidade". | J5: Status 422 com código PRODUTO_NAO_ENCONTRADO. O status HTTP está correto, só o código diverge da leitura literal da documentação. | K5: evidencias/api/BUG-003.png | L5: API-23 | M5: Sim (1 de 1) | N5: Sim (1 de 1)

Sheet Ambiguidades
A1: # | B1: Ponto ambíguo | C1: CA/Fonte | D1: O que a documentação diz | E1: Interpretação adotada (preencha) | F1: Caso relacionado | G1: Comportamento observado
A2: 1 | B2: Método de arredondamento | C2: CA11 | D2: &apos;Arredondados para 2 casas decimais&apos;, sem citar o método | E2: Comercial (half-up) | F2: CT-D1, API-12
A3: 2 | B3: Cupom com espaço no meio (&apos;BEM VINDO10&apos;) | C3: CA02 | D3: Só fala de espaços no início e no fim | E3: Cupom inválido | F3: CT-A2e
A4: 3 | B4: Mesmo produto adicionado várias vezes pela UI (3 + 3) | C4: CA10 | D4: Máximo de 5 unidades por produto por pedido | E4: O limite vale para a soma | F4: CT-C2c
A5: 4 | B5: Cupom vazio, null ou só espaços | C5: CA02/CA03 | D5: Não define | E5: Tratado como sem cupom | F5: API-17, CT-A7
A6: 5 | B6: Cupom com tipo errado (número/objeto) | C6: API | D6: Não define | E6: Erro de validação ou sem cupom; nunca 500 | F6: API-18
A7: 6 | B7: Trocar cupom sem remover o atual | C7: CA05 | D7: &apos;Para trocar, o cliente remove o cupom atual&apos; | E7: UI deve impedir a aplicação do segundo | F7: CT-A5
A8: 7 | B8: Mensagem de faltante quando já há frete grátis | C8: CA07 | D8: Só descreve o caso abaixo de R$ 200 | E8: Mensagem oculta ou R$ 0,00 | F8: CT-B6
A9: 8 | B9: Nome com espaços no fim (&apos;Maria &apos;) | C9: Regras existentes | D9: Precisa de nome e sobrenome | E9: Rejeitar (sem sobrenome real) | F9: CT-E5
A10: 9 | B10: Ordem de validação em /api/pedidos com vários erros | C10: API | D10: Não define a precedência | E10: Anotar a ordem observada | F10: API-46
A11: 10 | B11: Carrinho vazio: frete e total | C11: Regras | D11: Fórmula não cobre subtotal zero | E11: Frete 0 e total 0, ou bloquear finalização | F11: CT-F6
A12: 11 | B12: Cupom aplicado antes de ter itens | C12: CA01 | D12: Não define | E12: Cupom permanece e aplica ao adicionar | F12: CT-A8
B14: A coluna E vem com uma sugestão inicial. Confirme ou troque pela sua própria interpretação.

Sheet Resumo
A1: Resumo da execução
A3: Status | B3: Casos Manuais | C3: Casos API | D3: Total
A4: Passou | B4: =COUNTIF(&apos;Casos Manuais&apos;!$I$2:$I$53,A4) | C4: =COUNTIF(&apos;Casos API&apos;!$H$2:$H$50,A4) | D4: =B4+C4
A5: Falhou | B5: =COUNTIF(&apos;Casos Manuais&apos;!$I$2:$I$53,A5) | C5: =COUNTIF(&apos;Casos API&apos;!$H$2:$H$50,A5) | D5: =B5+C5
A6: Bloqueado | B6: =COUNTIF(&apos;Casos Manuais&apos;!$I$2:$I$53,A6) | C6: =COUNTIF(&apos;Casos API&apos;!$H$2:$H$50,A6) | D6: =B6+C6
A7: Dúvida | B7: =COUNTIF(&apos;Casos Manuais&apos;!$I$2:$I$53,A7) | C7: =COUNTIF(&apos;Casos API&apos;!$H$2:$H$50,A7) | D7: =B7+C7
A8: Não executado | B8: =COUNTIF(&apos;Casos Manuais&apos;!$I$2:$I$53,A8) | C8: =COUNTIF(&apos;Casos API&apos;!$H$2:$H$50,A8) | D8: =B8+C8
A9: Total | B9: =SUM(B4:B8) | C9: =SUM(C4:C8) | D9: =SUM(D4:D8)
A10: % executado | B10: =IF(B9=0,0,(B9-B8)/B9) | C10: =IF(C9=0,0,(C9-C8)/C9) | D10: =IF(D9=0,0,(D9-D8)/D9)
A12: Grupo (manuais) | B12: Total | C12: Passou | D12: Falhou
A13: A. Cupom | B13: =COUNTIF(&apos;Casos Manuais&apos;!$B$2:$B$53,A13) | C13: =COUNTIFS(&apos;Casos Manuais&apos;!$B$2:$B$53,A13,&apos;Casos Manuais&apos;!$I$2:$I$53,"Passou") | D13: =COUNTIFS(&apos;Casos Manuais&apos;!$B$2:$B$53,A13,&apos;Casos Manuais&apos;!$I$2:$I$53,"Falhou")
A14: B. Frete | B14: =COUNTIF(&apos;Casos Manuais&apos;!$B$2:$B$53,A14) | C14: =COUNTIFS(&apos;Casos Manuais&apos;!$B$2:$B$53,A14,&apos;Casos Manuais&apos;!$I$2:$I$53,"Passou") | D14: =COUNTIFS(&apos;Casos Manuais&apos;!$B$2:$B$53,A14,&apos;Casos Manuais&apos;!$I$2:$I$53,"Falhou")
A15: C. Quantidade | B15: =COUNTIF(&apos;Casos Manuais&apos;!$B$2:$B$53,A15) | C15: =COUNTIFS(&apos;Casos Manuais&apos;!$B$2:$B$53,A15,&apos;Casos Manuais&apos;!$I$2:$I$53,"Passou") | D15: =COUNTIFS(&apos;Casos Manuais&apos;!$B$2:$B$53,A15,&apos;Casos Manuais&apos;!$I$2:$I$53,"Falhou")
A16: D. Arredondamento | B16: =COUNTIF(&apos;Casos Manuais&apos;!$B$2:$B$53,A16) | C16: =COUNTIFS(&apos;Casos Manuais&apos;!$B$2:$B$53,A16,&apos;Casos Manuais&apos;!$I$2:$I$53,"Passou") | D16: =COUNTIFS(&apos;Casos Manuais&apos;!$B$2:$B$53,A16,&apos;Casos Manuais&apos;!$I$2:$I$53,"Falhou")
A17: E. Checkout | B17: =COUNTIF(&apos;Casos Manuais&apos;!$B$2:$B$53,A17) | C17: =COUNTIFS(&apos;Casos Manuais&apos;!$B$2:$B$53,A17,&apos;Casos Manuais&apos;!$I$2:$I$53,"Passou") | D17: =COUNTIFS(&apos;Casos Manuais&apos;!$B$2:$B$53,A17,&apos;Casos Manuais&apos;!$I$2:$I$53,"Falhou")
A18: F. Exploratório | B18: =COUNTIF(&apos;Casos Manuais&apos;!$B$2:$B$53,A18) | C18: =COUNTIFS(&apos;Casos Manuais&apos;!$B$2:$B$53,A18,&apos;Casos Manuais&apos;!$I$2:$I$53,"Passou") | D18: =COUNTIFS(&apos;Casos Manuais&apos;!$B$2:$B$53,A18,&apos;Casos Manuais&apos;!$I$2:$I$53,"Falhou")
A20: Bugs (exceto exemplo) | B20: Quantidade
A21: Total | B21: =COUNTA(Bugs!A3:A31)
A22: Crítica | B22: =COUNTIF(Bugs!C3:C31,"Crítica")
A23: Alta | B23: =COUNTIF(Bugs!C3:C31,"Alta")
A24: Média | B24: =COUNTIF(Bugs!C3:C31,"Média")
A25: Baixa | B25: =COUNTIF(Bugs!C3:C31,"Baixa")
